pyaem2/__init__.py
pyaem2/bagofrequests.py
pyaem2/contentrepo.py
pyaem2/exception.py
pyaem2/handlers.py
pyaem2/packagemanager.py
pyaem2/packagemanagerservicehtml.py
pyaem2/packagemanagerservicejson.py
pyaem2/packagemanagerservicejsp.py
pyaem2/pyaem2.py
pyaem2/result.py
pyaem2/sling.py
pyaem2/webconsole.py
pyaem2-2.0.1.dist-info/LICENSE
pyaem2-2.0.1.dist-info/METADATA
pyaem2-2.0.1.dist-info/WHEEL
pyaem2-2.0.1.dist-info/top_level.txt
pyaem2-2.0.1.dist-info/RECORD
